dashai_plugin_image_classification_hernan/__init__.py
dashai_plugin_image_classification_hernan/dataloader_class_template.py
dashai_plugin_image_classification_hernan/metric_class_template.py
dashai_plugin_image_classification_hernan/model_class_template.py
dashai_plugin_image_classification_hernan/task_class_template.py
dashai_plugin_image_classification_hernan-1.0.dist-info/METADATA
dashai_plugin_image_classification_hernan-1.0.dist-info/WHEEL
dashai_plugin_image_classification_hernan-1.0.dist-info/entry_points.txt
dashai_plugin_image_classification_hernan-1.0.dist-info/RECORD
